[
      {
        "title": "Queems",
        "description": "A companion app for LinkedIn’s ‘Queens’ puzzle. Track your scores, revisit completed puzzles, and beat your best times, built with an agentic workflow using MCP, spec-kit, and AI agents.",
        "image":"/assets/images/Projects/Queems.png",
        "githubLink":"https://queems.netlify.app/",
        "technologies": [
          {
            "name": "React",
            "logo": "https://img.shields.io/badge/React-20232A?style=for-the-badge&logo=react&logoColor=61DAFB"
          },
          {
            "name": "tailwindcss",
            "logo": null
          },
          {
            "name": "spec-driven-development",
            "logo": null
          },
          {
            "name": "spec-kit",
            "logo": null
          }
        ]
    },
    {
        "title": "Enigma Machine",
        "description": "A client-server desktop app recreating the historical Enigma cipher machine, featuring a real-time competitive platform where clients race to decrypt encoded messages.",
        "image":"/assets/images/Projects/Enigma.jpg",
        "githubLink":"https://github.com/RonHachmon/Enigma-Machine",
        "technologies": [
          {
            "name": "Java",
            "logo": "https://img.shields.io/badge/Java-ED8B00?style=for-the-badge&logo=java&logoColor=white"
          },
          {
            "name": "JavaFX ",
            "logo": null
          },
          {
            "name": "Apache Tomcat ",
            "logo": null
          }
        ]
    },
    {
      "title": "Cut it Out",
      "description": "A web app powered by an AI background removal model, with a full CI/CD pipeline using GitHub Actions, Docker, and AWS for automated containerized deployments.",
      "image":"/assets/images/Projects/Cut it Out.jpg",
      "githubLink":"https://github.com/RonHachmon/Cut-it-Out",
      "technologies": [
        {
          "name": "TypeScript",
          "logo": "https://img.shields.io/badge/TypeScript-007ACC?style=for-the-badge&logo=typescript&logoColor=white"
        },
        {
          "name": "React",
          "logo": "https://img.shields.io/badge/React-20232A?style=for-the-badge&logo=react&logoColor=61DAFB"
        },
        {
          "name": "NodeJS",
          "logo": "https://img.shields.io/badge/Node.js-339933?style=for-the-badge&logo=nodedotjs&logoColor=white"
        },
        {
          "name": "Docker",
          "logo": "https://img.shields.io/badge/Docker-2CA5E0?style=for-the-badge&logo=docker&logoColor=white"
        },
        {
          "name": "AWS ",
          "logo": null
        }
      ]
  },
    {
      "title": "Desktop Facebook",
      "description": "A Facebook desktop client in C# integrating the Graph API, applying OOP design patterns including Singleton, Strategy, Adapter, and Iterator for a clean, modular architecture.",
      "image":"/assets/images/Projects/facebook.jpg",
      "githubLink":"https://github.com/RonHachmon/Facebook-desktop-app",
      "technologies": [
        {
          "name": "C#",
          "logo": "https://img.shields.io/badge/C%23-239120?style=for-the-badge&logo=c-sharp&logoColor=white"
        },
        {
          "name": ".NET ",
          "logo": "https://img.shields.io/badge/.NET-512BD4?style=for-the-badge&logo=dotnet&logoColor=white"
        }
      ]
  },
    {
        "title": "Bull Detection",
        "description": "Fine-tuned an SSD object detection model using transfer learning and PyTorch to accurately detect and localize bulls in real-world images.",
        "image":"/assets/images/Projects/Bulls project.jpg",
        "githubLink":"https://github.com/RonHachmon/Transfer-Learing-SSD-model",
        "technologies": [
          {
            "name": "Python",
            "logo": "https://img.shields.io/badge/Python-3776AB?style=for-the-badge&logo=python&logoColor=white"
          },
          {
            "name": "Pytorch",
            "logo": "https://img.shields.io/badge/Pytorch-EE4C2C?style=for-the-badge&logo=pytorch&logoColor=white"
          }
        ]
    }
      
]
  